{
    "冰心诀": "10081",
    "云裳心经": "10080",
    "花间游": "10021",
    "离经易道": "10028",
    "毒经": "10175",
    "补天诀": "10176",
    "莫问": "10447",
    "相知": "10448",
    "无方": "10627",
    "灵素": "10626",
    "傲血战意": "10026",
    "铁牢律": "10062",
    "易筋经": "10003",
    "洗髓经": "10002",
    "焚影圣诀": "10242",
    "明尊琉璃体": "10243",
    "分山劲": "10390",
    "铁骨衣": "10389",
    "紫霞功": "10014",
    "太虚剑意": "10015",
    "天罗诡道": "10225",
    "惊羽诀": "10224",
    "问水诀": "10144",
    "山居剑意": "10145",
    "笑尘诀": "10268",
    "北傲诀": "10464",
    "凌海诀": "10533",
    "隐龙诀": "10585",
    "太玄经": "10615",
    "孤锋诀": "10698",
    "山海心诀": "10756"
}